NERDA/__init__.py
NERDA/datasets.py
NERDA/models.py
NERDA/networks.py
NERDA/performance.py
NERDA/precooked.py
NERDA/predictions.py
NERDA/preprocessing.py
NERDA/training.py
NERDA/utils.py
finetunetags-0.8.7.dist-info/LICENSE
finetunetags-0.8.7.dist-info/METADATA
finetunetags-0.8.7.dist-info/WHEEL
finetunetags-0.8.7.dist-info/top_level.txt
finetunetags-0.8.7.dist-info/RECORD
