Metadata-Version: 2.1
Name: finetunetags
Version: 0.8.7
Summary: A Framework for Finetuning Transformers for Named-Entity Recognition
Home-page: https://github.com/ebanalyse/NERDA
Author: Charlotte Parthoens
Author-email: charlotte.parthoens@1gmail.com
License: UNKNOWN
Platform: UNKNOWN
Classifier: Programming Language :: Python :: 3
Classifier: License :: OSI Approved :: MIT License
Requires-Python: >=3.6
Requires-Dist: torch (<=1.4)
Requires-Dist: transformers (>=4)
Requires-Dist: sklearn
Requires-Dist: nltk
Requires-Dist: pandas
Requires-Dist: progressbar
Requires-Dist: pyconll
